logidrivepy/__init__.py
logidrivepy/constants.py
logidrivepy/controller.py
logidrivepy/functions.py
logidrivepy/structs.py
logidrivepy/dll/LogitechSteeringWheelEnginesWrapper.dll
tests/__init__.py
tests/run_controller_test.py
tests/spin_wheel_test.py
logidrivepy-0.2.0.dist-info/LICENSE.txt
logidrivepy-0.2.0.dist-info/METADATA
logidrivepy-0.2.0.dist-info/WHEEL
logidrivepy-0.2.0.dist-info/top_level.txt
logidrivepy-0.2.0.dist-info/RECORD
