Metadata-Version: 2.1
Name: logidrivepy
Version: 0.2.0
Summary: A Python module for interfacing with Logitech steering wheels.
Home-page: https://github.com/cengizozel/logidrivepy
Author: Cengiz Ozel
Author-email: cozel@cs.rochester.edu
License: MIT
Keywords: logitech,g920,driving,steering-wheel,controller
Platform: UNKNOWN
Classifier: Development Status :: 4 - Beta
Classifier: Intended Audience :: Developers
Classifier: License :: OSI Approved :: MIT License
Classifier: Programming Language :: Python :: 3.8
Classifier: Programming Language :: Python :: 3.9
Classifier: Programming Language :: Python :: 3.10
License-File: LICENSE.txt
